graphedexcel/__init__.py
graphedexcel/__main__.py
graphedexcel/cli.py
graphedexcel/excel_parser.py
graphedexcel/graph_summarizer.py
graphedexcel/graph_visualizer.py
graphedexcel/graphbuilder.py
graphedexcel/logger_config.py
graphedexcel-1.2.3.dist-info/LICENSE
graphedexcel-1.2.3.dist-info/METADATA
graphedexcel-1.2.3.dist-info/WHEEL
graphedexcel-1.2.3.dist-info/entry_points.txt
graphedexcel-1.2.3.dist-info/RECORD
