Metadata-Version: 2.1
Name: graphedexcel
Version: 1.2.3
Summary: Tool to analyze and visualize dependencies between cells in Excel spreadsheets
Home-page: https://github.com/dalager/graphedexcel
License: MIT
Keywords: excel,graph,dependencies,visualization
Author: Christian Dalager
Author-email: christian@dalager.com
Requires-Python: >=3.10
Classifier: License :: OSI Approved :: MIT License
Classifier: Operating System :: OS Independent
Classifier: Programming Language :: Python :: 3
Classifier: Programming Language :: Python :: 3.10
Classifier: Programming Language :: Python :: 3.11
Classifier: Programming Language :: Python :: 3.12
Classifier: Programming Language :: Python :: 3.13
Requires-Dist: matplotlib (>=3.9)
Requires-Dist: networkx (>=3.3)
Requires-Dist: openpyxl (>=3.1)
Requires-Dist: scipy (>=1.14)
Project-URL: Documentation, https://github.com/dalager/graphedexcel
Project-URL: Repository, https://github.com/dalager/graphedexcel
